nam/__init__.py
nam/types.py
nam/config/__init__.py
nam/config/base.py
nam/config/default.py
nam/data/__init__.py
nam/data/base.py
nam/data/datasets.py
nam/data/folded.py
nam/data/utils.py
nam/models/__init__.py
nam/models/base.py
nam/models/dnn.py
nam/models/featurenn.py
nam/models/nam.py
nam/models/saver.py
nam/models/utils.py
nam/models/activation/__init__.py
nam/models/activation/exu.py
nam/models/activation/relu.py
nam/trainer/__init__.py
nam/trainer/litnam.py
nam/trainer/losses.py
nam/trainer/metrics.py
nam/trainer/trainer.py
nam/utils/__init__.py
nam/utils/args.py
nam/utils/graphing.py
nam/utils/loggers/__init__.py
nam/utils/loggers/base.py
nam/utils/loggers/tensorboard.py
nam/utils/loggers/wandb.py
nam-0.0.3.dist-info/LICENSE
nam-0.0.3.dist-info/METADATA
nam-0.0.3.dist-info/WHEEL
nam-0.0.3.dist-info/top_level.txt
nam-0.0.3.dist-info/RECORD
