Metadata-Version: 2.1
Name: nam
Version: 0.0.3
Summary: Neural Additive Models (Google Research)
Home-page: https://github.com/AmrMKayid/nam
Author: Amr Kayid
License: UNKNOWN
Platform: UNKNOWN
Classifier: Programming Language :: Python :: 3.6
Classifier: License :: OSI Approved :: MIT License
Classifier: Operating System :: OS Independent
Requires-Dist: torch
Requires-Dist: pytorch-lightning
Requires-Dist: wandb
Requires-Dist: matplotlib
Requires-Dist: sklearn
Requires-Dist: numpy
Requires-Dist: pandas
Requires-Dist: loguru
